MANIFEST.in
README.md
setup.py
GephiStreamer.egg-info/PKG-INFO
GephiStreamer.egg-info/SOURCES.txt
GephiStreamer.egg-info/dependency_links.txt
GephiStreamer.egg-info/requires.txt
GephiStreamer.egg-info/top_level.txt
gephistreamer/__init__.py
gephistreamer/graph.py
gephistreamer/streamer.py