Metadata-Version: 1.1
Name: GephiStreamer
Version: 2.0.2
Summary: Tools to stream data to gephi
Home-page: https://github.com/totetmatt/GephiStreamer
Author: Matthieu Totet (@totetmatt)
Author-email: matthieu.totet@gmail.com
License: UNKNOWN
Platform: UNKNOWN
Classifier: Programming Language :: Python
Classifier: Operating System :: OS Independent
Classifier: Programming Language :: Python :: 3.4
Classifier: Topic :: Communications
